BacklogPy/__init__.py
BacklogPy/backlog.py
BacklogPy/base.py
BacklogPy/version.py
BacklogPy/api/__init__.py
BacklogPy/api/activities.py
BacklogPy/api/groups.py
BacklogPy/api/issues.py
BacklogPy/api/notifications.py
BacklogPy/api/priorities.py
BacklogPy/api/projects.py
BacklogPy/api/rateLimit.py
BacklogPy/api/resolutions.py
BacklogPy/api/space.py
BacklogPy/api/stars.py
BacklogPy/api/statuses.py
BacklogPy/api/teams.py
BacklogPy/api/users.py
BacklogPy/api/watchings.py
BacklogPy/api/wikis.py
BacklogPy-1.1.1.data/data/LICENSE
BacklogPy-1.1.1.data/data/README.rst
BacklogPy-1.1.1.dist-info/LICENSE
BacklogPy-1.1.1.dist-info/METADATA
BacklogPy-1.1.1.dist-info/WHEEL
BacklogPy-1.1.1.dist-info/top_level.txt
BacklogPy-1.1.1.dist-info/RECORD
