Metadata-Version: 2.1
Name: BacklogPy
Version: 1.1.1
Summary: Backlog API v2 Client Library
Home-page: https://github.com/koxudaxi/BacklogPy
Author: Koudai Aono
Author-email: koxudaxi@gmail.com
License: UNKNOWN
Platform: UNKNOWN
Classifier: Development Status :: 5 - Production/Stable
Classifier: Natural Language :: English
Classifier: License :: OSI Approved :: MIT License
Classifier: Programming Language :: Python
Classifier: Programming Language :: Python :: 2.7
Classifier: Programming Language :: Python :: 3
Classifier: Programming Language :: Python :: 3.5
Classifier: Programming Language :: Python :: 3.6
Classifier: Programming Language :: Python :: 3.7
Classifier: Programming Language :: Python :: 3.8
Classifier: Programming Language :: Python :: 3.9
Classifier: Programming Language :: Python :: Implementation :: CPython
Requires-Dist: requests
Requires-Dist: Deprecated
Provides-Extra: deploy
Requires-Dist: wheel ; extra == 'deploy'
Requires-Dist: twine ; extra == 'deploy'
